{
  "summary": {
    "valid": false,
    "issue_count": 39,
    "scope": "all",
    "required_languages": [
      "curl",
      "javascript",
      "python"
    ]
  },
  "issues": [
    {
      "file": "docs/SEO_GUIDE.md",
      "message": "Missing language tabs. Add a tab group with languages: curl, javascript, python"
    },
    {
      "file": "docs/VARIABLES_GUIDE.md",
      "message": "Missing language tabs. Add a tab group with languages: curl, javascript, python"
    },
    {
      "file": "docs/getting-started/quickstart.md",
      "message": "No tab group contains required languages: curl, javascript, python"
    },
    {
      "file": "docs/how-to/assemble-intent-experiences.md",
      "message": "Missing language tabs. Add a tab group with languages: curl, javascript, python"
    },
    {
      "file": "docs/how-to/configure-ask-ai-module.md",
      "message": "Missing language tabs. Add a tab group with languages: curl, javascript, python"
    },
    {
      "file": "docs/how-to/configure-webhook-trigger.md",
      "message": "No tab group contains required languages: curl, javascript, python"
    },
    {
      "file": "docs/how-to/install-ask-ai-runtime-pack.md",
      "message": "No tab group contains required languages: curl, javascript, python"
    },
    {
      "file": "docs/how-to/migrate-from-confluence.md",
      "message": "No tab group contains required languages: curl, javascript, python"
    },
    {
      "file": "docs/operations/CANONICAL_FLOW.md",
      "message": "Missing language tabs. Add a tab group with languages: curl, javascript, python"
    },
    {
      "file": "docs/operations/CENTRALIZED_CLIENT_BUNDLES.md",
      "message": "No tab group contains required languages: curl, javascript, python"
    },
    {
      "file": "docs/operations/MULTI_PROTOCOL_ARCHITECTURE.md",
      "message": "Missing language tabs. Add a tab group with languages: curl, javascript, python"
    },
    {
      "file": "docs/operations/MULTI_PROTOCOL_WIZARD_GUIDE.md",
      "message": "Missing language tabs. Add a tab group with languages: curl, javascript, python"
    },
    {
      "file": "docs/operations/OPERATOR_RUNBOOK.md",
      "message": "Missing language tabs. Add a tab group with languages: curl, javascript, python"
    },
    {
      "file": "docs/operations/PIPELINE_CAPABILITIES_CATALOG.md",
      "message": "Missing language tabs. Add a tab group with languages: curl, javascript, python"
    },
    {
      "file": "docs/operations/PLAN_TIERS.md",
      "message": "Missing language tabs. Add a tab group with languages: curl, javascript, python"
    },
    {
      "file": "docs/operations/UNIFIED_CLIENT_CONFIG.md",
      "message": "Missing language tabs. Add a tab group with languages: curl, javascript, python"
    },
    {
      "file": "docs/reference/auto-doc-pipeline-study-guide.md",
      "message": "Missing language tabs. Add a tab group with languages: curl, javascript, python"
    },
    {
      "file": "docs/reference/intent-experiences/automate-developer.md",
      "message": "Missing language tabs. Add a tab group with languages: curl, javascript, python"
    },
    {
      "file": "docs/reference/intent-experiences/automate-operator.md",
      "message": "Missing language tabs. Add a tab group with languages: curl, javascript, python"
    },
    {
      "file": "docs/reference/intent-experiences/automate-support.md",
      "message": "Missing language tabs. Add a tab group with languages: curl, javascript, python"
    },
    {
      "file": "docs/reference/intent-experiences/configure-beginner.md",
      "message": "No tab group contains required languages: curl, javascript, python"
    },
    {
      "file": "docs/reference/intent-experiences/configure-operator.md",
      "message": "No tab group contains required languages: curl, javascript, python"
    },
    {
      "file": "docs/reference/intent-experiences/configure-support.md",
      "message": "No tab group contains required languages: curl, javascript, python"
    },
    {
      "file": "docs/reference/intent-experiences/index.md",
      "message": "Missing language tabs. Add a tab group with languages: curl, javascript, python"
    },
    {
      "file": "docs/reference/intent-experiences/integrate-practitioner.md",
      "message": "No tab group contains required languages: curl, javascript, python"
    },
    {
      "file": "docs/reference/intent-experiences/integrate-support.md",
      "message": "No tab group contains required languages: curl, javascript, python"
    },
    {
      "file": "docs/reference/intent-experiences/optimize-developer.md",
      "message": "Missing language tabs. Add a tab group with languages: curl, javascript, python"
    },
    {
      "file": "docs/reference/intent-experiences/optimize-operator.md",
      "message": "Missing language tabs. Add a tab group with languages: curl, javascript, python"
    },
    {
      "file": "docs/reference/intent-experiences/optimize-support.md",
      "message": "Missing language tabs. Add a tab group with languages: curl, javascript, python"
    },
    {
      "file": "docs/reference/intent-experiences/secure-beginner.md",
      "message": "Missing language tabs. Add a tab group with languages: curl, javascript, python"
    },
    {
      "file": "docs/reference/intent-experiences/secure-developer.md",
      "message": "No tab group contains required languages: curl, javascript, python"
    },
    {
      "file": "docs/reference/intent-experiences/secure-operator.md",
      "message": "No tab group contains required languages: curl, javascript, python"
    },
    {
      "file": "docs/reference/intent-experiences/secure-practitioner.md",
      "message": "No tab group contains required languages: curl, javascript, python"
    },
    {
      "file": "docs/reference/intent-experiences/secure-support.md",
      "message": "No tab group contains required languages: curl, javascript, python"
    },
    {
      "file": "docs/reference/intent-experiences/troubleshoot-beginner.md",
      "message": "Missing language tabs. Add a tab group with languages: curl, javascript, python"
    },
    {
      "file": "docs/reference/intent-experiences/troubleshoot-practitioner.md",
      "message": "Missing language tabs. Add a tab group with languages: curl, javascript, python"
    },
    {
      "file": "docs/reference/intent-experiences/troubleshoot-support.md",
      "message": "No tab group contains required languages: curl, javascript, python"
    },
    {
      "file": "docs/reference/network-transparency.md",
      "message": "Missing language tabs. Add a tab group with languages: curl, javascript, python"
    },
    {
      "file": "docs/troubleshooting/webhook-not-firing.md",
      "message": "No tab group contains required languages: curl, javascript, python"
    }
  ]
}
